[
  {
    "title": "Tarea 1",
    "body": "Descripción de la tarea 1",
    "status": true
  },
  {
    "title": "Tarea 2",
    "body": "Descripción de la tarea 2",
    "status": false
  },
  {
    "title": "Tarea 3",
    "body": "Descripción de la tarea 3",
    "status": true
  },
  {
    "title": "Tarea 4",
    "body": "Descripción de la tarea 4",
    "status": false
  },
  {
    "title": "Tarea 5",
    "body": "Descripción de la tarea 5",
    "status": true
  },
  {
    "title": "Tarea 6",
    "body": "Descripción de la tarea 6",
    "status": false
  },
  {
    "title": "Tarea 7",
    "body": "Descripción de la tarea 7",
    "status": true
  },
  {
    "title": "Tarea 8",
    "body": "Descripción de la tarea 8",
    "status": false
  },
  {
    "title": "Tarea 9",
    "body": "Descripción de la tarea 9",
    "status": true
  },
  {
    "title": "Tarea 10",
    "body": "Descripción de la tarea 10",
    "status": false
  }
]